Metadata-Version: 2.1
Name: watermarkImage
Version: 1.0.1
Summary: Watermark batch of images
Home-page: https://github.com/roybs2/watermark-image
Author: Roy Ben Shlomo
License: MIT
Download-URL: https://github.com/roybs2/watermark-image/archive/v1.0.1.tar.gz
Platform: UNKNOWN
Classifier: License :: OSI Approved :: MIT License
Classifier: Programming Language :: Python :: 3
Classifier: Programming Language :: Python :: 3.5
